purses/__init__.py
purses/__main__.py
purses/bindings.py
purses/callbackutil.py
purses/controller.py
purses/model.py
purses/userspace.py
purses/view.py
purses-0.0.11.dist-info/DESCRIPTION.rst
purses-0.0.11.dist-info/METADATA
purses-0.0.11.dist-info/RECORD
purses-0.0.11.dist-info/WHEEL
purses-0.0.11.dist-info/entry_points.txt
purses-0.0.11.dist-info/metadata.json
purses-0.0.11.dist-info/top_level.txt
