Metadata-Version: 2.0
Name: purses
Version: 0.0.11
Summary: Purses, a Pandas Curses
Home-page: UNKNOWN
Author: pgdr@equinor.com
Author-email: pgdr@equinor.com
License: UNKNOWN
Platform: UNKNOWN
Requires-Dist: pandas
Requires-Dist: npyscreen
